spectral_explorer/__init__.py
spectral_explorer/configs.py
spectral_explorer/gui.py
spectral_explorer/run.py
spectral_explorer/utils.py
spectral_explorer-0.4.0.dist-info/METADATA
spectral_explorer-0.4.0.dist-info/WHEEL
spectral_explorer-0.4.0.dist-info/licenses/LICENSE
spectral_explorer-0.4.0.dist-info/RECORD
