Metadata-Version: 2.3
Name: spectral_explorer
Version: 0.4.0
Summary: A package for running a text game about exploring generated worlds
Author-email: Nicholas Hotelling <nicholashotelling@gmail.com>, Baylor Pond <baylorpond@gmail.com>, Nicholas Perlich <nicholasperlich2003@gmail.com>
License: MIT
Classifier: License :: OSI Approved :: MIT License
Classifier: Operating System :: OS Independent
Classifier: Programming Language :: Python :: 3
Requires-Python: >=3.7
Requires-Dist: devtools>=0.8.2
Requires-Dist: openai>=0.27.0
Requires-Dist: pillow>=9.0.0
Requires-Dist: python-dotenv>=0.21.0
